mgt2001/__init__.py
mgt2001/_version.py
mgt2001/des.py
mgt2001/per.py
mgt2001/prob.py
mgt2001/samp.py
mgt2001/team.py
mgt2001/time_series.py
mgt2001/tree.py
mgt2001/hyp/__init__.py
mgt2001/hyp/anova.py
mgt2001/hyp/chi2.py
mgt2001/hyp/ind.py
mgt2001/hyp/non.py
mgt2001/hyp/p.py
mgt2001/hyp/t.py
mgt2001/model/__init__.py
mgt2001/model/model_building.py
mgt2001/model/table.py
mgt2001/notes/__init__.py
mgt2001-1.0.0.dist-info/LICENSE
mgt2001-1.0.0.dist-info/METADATA
mgt2001-1.0.0.dist-info/WHEEL
mgt2001-1.0.0.dist-info/top_level.txt
mgt2001-1.0.0.dist-info/RECORD
