Metadata-Version: 2.1
Name: mgt2001
Version: 1.0.0
Summary: A small package for MGT 2001 and MGT 2002 use only
Home-page: https://github.com/icheft/mgt2001
Author: Brian L. Chen
Author-email: brian.lxchen@gmail.com
License: UNKNOWN
Platform: UNKNOWN
Classifier: Programming Language :: Python :: 3
Classifier: License :: OSI Approved :: MIT License
Classifier: Operating System :: OS Independent
Requires-Python: >=3.6
Requires-Dist: numpy
Requires-Dist: pandas
Requires-Dist: matplotlib
Requires-Dist: adjustText
Requires-Dist: scipy
Requires-Dist: ete3
Requires-Dist: seaborn
Requires-Dist: stemgraphic
Requires-Dist: statsmodels
Requires-Dist: plotly
Requires-Dist: pymdown-extensions
Requires-Dist: mkdocs
Requires-Dist: mkdocs-material
Requires-Dist: sympy
Requires-Dist: mplfinance
